README
setup.py
python_org/__init__.py
python_org/_version.py
python_org/org_util.py
python_org/orgclass.py
python_org/orgreader.py
python_org.egg-info/PKG-INFO
python_org.egg-info/SOURCES.txt
python_org.egg-info/dependency_links.txt
python_org.egg-info/top_level.txt
python_org.egg-info/zip-safe
python_org/test/__init__.py
python_org/test/orgclass_test.py
python_org/test/orgreader_test.py